<?xml version="1.0" encoding="utf-8"?>
<AudioMarkers count="63">
  <Marker pid="108:0.0" seqId="1">
    <Start>0:0:0.0</Start>
    <End>0:0:6.883</End>
    <TimeSpan>0:0:0.0_0:0:6.883</TimeSpan>
  </Marker>
  <Marker pid="108:0.1" seqId="2">
    <Start>0:0:6.883</Start>
    <End>0:0:53.734</End>
    <TimeSpan>0:0:6.883_0:0:53.734</TimeSpan>
  </Marker>
  <Marker pid="108:0.2" seqId="3">
    <Start>0:0:53.734</Start>
    <End>0:1:55.120</End>
    <TimeSpan>0:0:53.734_0:1:55.120</TimeSpan>
  </Marker>
  <Marker pid="108:1.0" seqId="4">
    <Start>0:1:55.120</Start>
    <End>0:1:58.945</End>
    <TimeSpan>0:1:55.120_0:1:58.945</TimeSpan>
  </Marker>
  <Marker pid="108:1.1" seqId="5">
    <Start>0:1:58.945</Start>
    <End>0:2:41.377</End>
    <TimeSpan>0:1:58.945_0:2:41.377</TimeSpan>
  </Marker>
  <Marker pid="108:1.2" seqId="6">
    <Start>0:2:41.377</Start>
    <End>0:3:30.218</End>
    <TimeSpan>0:2:41.377_0:3:30.218</TimeSpan>
  </Marker>
  <Marker pid="108:1.3" seqId="7">
    <Start>0:3:30.218</Start>
    <End>0:3:36.640</End>
    <TimeSpan>0:3:30.218_0:3:36.640</TimeSpan>
  </Marker>
  <Marker pid="108:1.4" seqId="8">
    <Start>0:3:36.640</Start>
    <End>0:3:54.10</End>
    <TimeSpan>0:3:36.640_0:3:54.10</TimeSpan>
  </Marker>
  <Marker pid="108:1.5" seqId="9">
    <Start>0:3:54.10</Start>
    <End>0:4:9.36</End>
    <TimeSpan>0:3:54.10_0:4:9.36</TimeSpan>
  </Marker>
  <Marker pid="108:1.6" seqId="10">
    <Start>0:4:9.36</Start>
    <End>0:4:27.588</End>
    <TimeSpan>0:4:9.36_0:4:27.588</TimeSpan>
  </Marker>
  <Marker pid="108:1.7" seqId="11">
    <Start>0:4:27.588</Start>
    <End>0:4:55.522</End>
    <TimeSpan>0:4:27.588_0:4:55.522</TimeSpan>
  </Marker>
  <Marker pid="108:1.8" seqId="12">
    <Start>0:4:55.522</Start>
    <End>0:5:39.861</End>
    <TimeSpan>0:4:55.522_0:5:39.861</TimeSpan>
  </Marker>
  <Marker pid="108:1.9" seqId="13">
    <Start>0:5:39.861</Start>
    <End>0:6:5.710</End>
    <TimeSpan>0:5:39.861_0:6:5.710</TimeSpan>
  </Marker>
  <Marker pid="108:2.0" seqId="14">
    <Start>0:6:5.710</Start>
    <End>0:6:10.585</End>
    <TimeSpan>0:6:5.710_0:6:10.585</TimeSpan>
  </Marker>
  <Marker pid="108:2.1" seqId="15">
    <Start>0:6:10.585</Start>
    <End>0:7:4.989</End>
    <TimeSpan>0:6:10.585_0:7:4.989</TimeSpan>
  </Marker>
  <Marker pid="108:2.2" seqId="16">
    <Start>0:7:4.989</Start>
    <End>0:7:35.811</End>
    <TimeSpan>0:7:4.989_0:7:35.811</TimeSpan>
  </Marker>
  <Marker pid="108:2.3" seqId="17">
    <Start>0:7:35.811</Start>
    <End>0:8:23.879</End>
    <TimeSpan>0:7:35.811_0:8:23.879</TimeSpan>
  </Marker>
  <Marker pid="108:2.4" seqId="18">
    <Start>0:8:23.879</Start>
    <End>0:8:53.188</End>
    <TimeSpan>0:8:23.879_0:8:53.188</TimeSpan>
  </Marker>
  <Marker pid="108:2.5" seqId="19">
    <Start>0:8:53.188</Start>
    <End>0:9:29.954</End>
    <TimeSpan>0:8:53.188_0:9:29.954</TimeSpan>
  </Marker>
  <Marker pid="108:2.6" seqId="20">
    <Start>0:9:29.954</Start>
    <End>0:9:50.603</End>
    <TimeSpan>0:9:29.954_0:9:50.603</TimeSpan>
  </Marker>
  <Marker pid="108:2.7" seqId="21">
    <Start>0:9:50.603</Start>
    <End>0:10:9.231</End>
    <TimeSpan>0:9:50.603_0:10:9.231</TimeSpan>
  </Marker>
  <Marker pid="108:2.8" seqId="22">
    <Start>0:10:9.231</Start>
    <End>0:10:23.167</End>
    <TimeSpan>0:10:9.231_0:10:23.167</TimeSpan>
  </Marker>
  <Marker pid="108:2.9" seqId="23">
    <Start>0:10:23.167</Start>
    <End>0:10:48.972</End>
    <TimeSpan>0:10:23.167_0:10:48.972</TimeSpan>
  </Marker>
  <Marker pid="108:2.10" seqId="24">
    <Start>0:10:48.972</Start>
    <End>0:11:20.502</End>
    <TimeSpan>0:10:48.972_0:11:20.502</TimeSpan>
  </Marker>
  <Marker pid="108:2.11" seqId="25">
    <Start>0:11:20.502</Start>
    <End>0:11:57.167</End>
    <TimeSpan>0:11:20.502_0:11:57.167</TimeSpan>
  </Marker>
  <Marker pid="108:3.0" seqId="26">
    <Start>0:11:57.167</Start>
    <End>0:12:1.661</End>
    <TimeSpan>0:11:57.167_0:12:1.661</TimeSpan>
  </Marker>
  <Marker pid="108:3.1" seqId="27">
    <Start>0:12:1.661</Start>
    <End>0:12:42.149</End>
    <TimeSpan>0:12:1.661_0:12:42.149</TimeSpan>
  </Marker>
  <Marker pid="108:3.2" seqId="28">
    <Start>0:12:42.149</Start>
    <End>0:13:25.833</End>
    <TimeSpan>0:12:42.149_0:13:25.833</TimeSpan>
  </Marker>
  <Marker pid="108:3.3" seqId="29">
    <Start>0:13:25.833</Start>
    <End>0:13:41.431</End>
    <TimeSpan>0:13:25.833_0:13:41.431</TimeSpan>
  </Marker>
  <Marker pid="108:3.4" seqId="30">
    <Start>0:13:41.431</Start>
    <End>0:14:13.232</End>
    <TimeSpan>0:13:41.431_0:14:13.232</TimeSpan>
  </Marker>
  <Marker pid="108:3.5" seqId="31">
    <Start>0:14:13.232</Start>
    <End>0:15:3.753</End>
    <TimeSpan>0:14:13.232_0:15:3.753</TimeSpan>
  </Marker>
  <Marker pid="108:3.6" seqId="32">
    <Start>0:15:3.753</Start>
    <End>0:16:23.380</End>
    <TimeSpan>0:15:3.753_0:16:23.380</TimeSpan>
  </Marker>
  <Marker pid="108:3.7" seqId="33">
    <Start>0:16:23.380</Start>
    <End>0:16:48.975</End>
    <TimeSpan>0:16:23.380_0:16:48.975</TimeSpan>
  </Marker>
  <Marker pid="108:3.8" seqId="34">
    <Start>0:16:48.975</Start>
    <End>0:17:25.838</End>
    <TimeSpan>0:16:48.975_0:17:25.838</TimeSpan>
  </Marker>
  <Marker pid="108:3.9" seqId="35">
    <Start>0:17:25.838</Start>
    <End>0:17:54.626</End>
    <TimeSpan>0:17:25.838_0:17:54.626</TimeSpan>
  </Marker>
  <Marker pid="108:3.10" seqId="36">
    <Start>0:17:54.626</Start>
    <End>0:18:20.718</End>
    <TimeSpan>0:17:54.626_0:18:20.718</TimeSpan>
  </Marker>
  <Marker pid="108:4.0" seqId="37">
    <Start>0:18:20.718</Start>
    <End>0:18:25.737</End>
    <TimeSpan>0:18:20.718_0:18:25.737</TimeSpan>
  </Marker>
  <Marker pid="108:4.1" seqId="38">
    <Start>0:18:25.737</Start>
    <End>0:19:39.581</End>
    <TimeSpan>0:18:25.737_0:19:39.581</TimeSpan>
  </Marker>
  <Marker pid="108:4.2" seqId="39">
    <Start>0:19:39.581</Start>
    <End>0:20:46.88</End>
    <TimeSpan>0:19:39.581_0:20:46.88</TimeSpan>
  </Marker>
  <Marker pid="108:4.3" seqId="40">
    <Start>0:20:46.88</Start>
    <End>0:21:22.884</End>
    <TimeSpan>0:20:46.88_0:21:22.884</TimeSpan>
  </Marker>
  <Marker pid="108:4.4" seqId="41">
    <Start>0:21:22.884</Start>
    <End>0:22:31.369</End>
    <TimeSpan>0:21:22.884_0:22:31.369</TimeSpan>
  </Marker>
  <Marker pid="108:4.5" seqId="42">
    <Start>0:22:31.369</Start>
    <End>0:23:11.704</End>
    <TimeSpan>0:22:31.369_0:23:11.704</TimeSpan>
  </Marker>
  <Marker pid="108:5.0" seqId="43">
    <Start>0:23:11.704</Start>
    <End>0:23:15.992</End>
    <TimeSpan>0:23:11.704_0:23:15.992</TimeSpan>
  </Marker>
  <Marker pid="108:5.1" seqId="44">
    <Start>0:23:15.992</Start>
    <End>0:23:42.984</End>
    <TimeSpan>0:23:15.992_0:23:42.984</TimeSpan>
  </Marker>
  <Marker pid="108:5.2" seqId="45">
    <Start>0:23:42.984</Start>
    <End>0:24:9.628</End>
    <TimeSpan>0:23:42.984_0:24:9.628</TimeSpan>
  </Marker>
  <Marker pid="108:5.3" seqId="46">
    <Start>0:24:9.628</Start>
    <End>0:24:38.815</End>
    <TimeSpan>0:24:9.628_0:24:38.815</TimeSpan>
  </Marker>
  <Marker pid="108:5.4" seqId="47">
    <Start>0:24:38.815</Start>
    <End>0:25:0.874</End>
    <TimeSpan>0:24:38.815_0:25:0.874</TimeSpan>
  </Marker>
  <Marker pid="108:5.5" seqId="48">
    <Start>0:25:0.874</Start>
    <End>0:25:55.352</End>
    <TimeSpan>0:25:0.874_0:25:55.352</TimeSpan>
  </Marker>
  <Marker pid="108:5.6" seqId="49">
    <Start>0:25:55.352</Start>
    <End>0:26:38.614</End>
    <TimeSpan>0:25:55.352_0:26:38.614</TimeSpan>
  </Marker>
  <Marker pid="108:5.7" seqId="50">
    <Start>0:26:38.614</Start>
    <End>0:27:11.417</End>
    <TimeSpan>0:26:38.614_0:27:11.417</TimeSpan>
  </Marker>
  <Marker pid="108:5.8" seqId="51">
    <Start>0:27:11.417</Start>
    <End>0:27:39.139</End>
    <TimeSpan>0:27:11.417_0:27:39.139</TimeSpan>
  </Marker>
  <Marker pid="108:5.9" seqId="52">
    <Start>0:27:39.139</Start>
    <End>0:28:9.595</End>
    <TimeSpan>0:27:39.139_0:28:9.595</TimeSpan>
  </Marker>
  <Marker pid="108:5.10" seqId="53">
    <Start>0:28:9.595</Start>
    <End>0:28:54.300</End>
    <TimeSpan>0:28:9.595_0:28:54.300</TimeSpan>
  </Marker>
  <Marker pid="108:6.0" seqId="54">
    <Start>0:28:54.300</Start>
    <End>0:28:58.294</End>
    <TimeSpan>0:28:54.300_0:28:58.294</TimeSpan>
  </Marker>
  <Marker pid="108:6.1" seqId="55">
    <Start>0:28:58.294</Start>
    <End>0:29:17.981</End>
    <TimeSpan>0:28:58.294_0:29:17.981</TimeSpan>
  </Marker>
  <Marker pid="108:6.2" seqId="56">
    <Start>0:29:17.981</Start>
    <End>0:30:18.795</End>
    <TimeSpan>0:29:17.981_0:30:18.795</TimeSpan>
  </Marker>
  <Marker pid="108:6.3" seqId="57">
    <Start>0:30:18.795</Start>
    <End>0:31:4.27</End>
    <TimeSpan>0:30:18.795_0:31:4.27</TimeSpan>
  </Marker>
  <Marker pid="108:6.4" seqId="58">
    <Start>0:31:4.27</Start>
    <End>0:31:33.381</End>
    <TimeSpan>0:31:4.27_0:31:33.381</TimeSpan>
  </Marker>
  <Marker pid="108:6.5" seqId="59">
    <Start>0:31:33.381</Start>
    <End>0:32:14.218</End>
    <TimeSpan>0:31:33.381_0:32:14.218</TimeSpan>
  </Marker>
  <Marker pid="108:6.6" seqId="60">
    <Start>0:32:14.218</Start>
    <End>0:32:42.266</End>
    <TimeSpan>0:32:14.218_0:32:42.266</TimeSpan>
  </Marker>
  <Marker pid="108:6.7" seqId="61">
    <Start>0:32:42.266</Start>
    <End>0:33:21.129</End>
    <TimeSpan>0:32:42.266_0:33:21.129</TimeSpan>
  </Marker>
  <Marker pid="108:6.8" seqId="62">
    <Start>0:33:21.129</Start>
    <End>0:34:1.175</End>
    <TimeSpan>0:33:21.129_0:34:1.175</TimeSpan>
  </Marker>
  <Marker pid="108:6.9" seqId="63">
    <Start>0:34:1.175</Start>
    <End>0:34:5.601</End>
    <TimeSpan>0:34:1.175_0:34:5.601</TimeSpan>
  </Marker>
</AudioMarkers>