<?xml version="1.0" encoding="utf-8"?>
<AudioMarkers count="60">
  <Marker pid="109:0.0" seqId="1">
    <Start>0:0:0.0</Start>
    <End>0:0:7.247</End>
    <TimeSpan>0:0:0.0_0:0:7.247</TimeSpan>
  </Marker>
  <Marker pid="109:0.1" seqId="2">
    <Start>0:0:7.247</Start>
    <End>0:1:19.511</End>
    <TimeSpan>0:0:7.247_0:1:19.511</TimeSpan>
  </Marker>
  <Marker pid="109:1.0" seqId="3">
    <Start>0:1:19.511</Start>
    <End>0:1:24.240</End>
    <TimeSpan>0:1:19.511_0:1:24.240</TimeSpan>
  </Marker>
  <Marker pid="109:1.1" seqId="4">
    <Start>0:1:24.240</Start>
    <End>0:1:49.577</End>
    <TimeSpan>0:1:24.240_0:1:49.577</TimeSpan>
  </Marker>
  <Marker pid="109:1.2" seqId="5">
    <Start>0:1:49.577</Start>
    <End>0:2:14.775</End>
    <TimeSpan>0:1:49.577_0:2:14.775</TimeSpan>
  </Marker>
  <Marker pid="109:1.3" seqId="6">
    <Start>0:2:14.775</Start>
    <End>0:2:55.913</End>
    <TimeSpan>0:2:14.775_0:2:55.913</TimeSpan>
  </Marker>
  <Marker pid="109:1.4" seqId="7">
    <Start>0:2:55.913</Start>
    <End>0:3:26.582</End>
    <TimeSpan>0:2:55.913_0:3:26.582</TimeSpan>
  </Marker>
  <Marker pid="109:1.5" seqId="8">
    <Start>0:3:26.582</Start>
    <End>0:3:55.237</End>
    <TimeSpan>0:3:26.582_0:3:55.237</TimeSpan>
  </Marker>
  <Marker pid="109:2.0" seqId="9">
    <Start>0:3:55.237</Start>
    <End>0:4:0.160</End>
    <TimeSpan>0:3:55.237_0:4:0.160</TimeSpan>
  </Marker>
  <Marker pid="109:2.1" seqId="10">
    <Start>0:4:0.160</Start>
    <End>0:4:18.858</End>
    <TimeSpan>0:4:0.160_0:4:18.858</TimeSpan>
  </Marker>
  <Marker pid="109:2.2" seqId="11">
    <Start>0:4:18.858</Start>
    <End>0:4:39.542</End>
    <TimeSpan>0:4:18.858_0:4:39.542</TimeSpan>
  </Marker>
  <Marker pid="109:2.3" seqId="12">
    <Start>0:4:39.542</Start>
    <End>0:4:50.413</End>
    <TimeSpan>0:4:39.542_0:4:50.413</TimeSpan>
  </Marker>
  <Marker pid="109:2.4" seqId="13">
    <Start>0:4:50.413</Start>
    <End>0:5:6.464</End>
    <TimeSpan>0:4:50.413_0:5:6.464</TimeSpan>
  </Marker>
  <Marker pid="109:2.5" seqId="14">
    <Start>0:5:6.464</Start>
    <End>0:5:15.752</End>
    <TimeSpan>0:5:6.464_0:5:15.752</TimeSpan>
  </Marker>
  <Marker pid="109:2.6" seqId="15">
    <Start>0:5:15.752</Start>
    <End>0:5:34.950</End>
    <TimeSpan>0:5:15.752_0:5:34.950</TimeSpan>
  </Marker>
  <Marker pid="109:2.7" seqId="16">
    <Start>0:5:34.950</Start>
    <End>0:5:51.619</End>
    <TimeSpan>0:5:34.950_0:5:51.619</TimeSpan>
  </Marker>
  <Marker pid="109:2.8" seqId="17">
    <Start>0:5:51.619</Start>
    <End>0:6:20.106</End>
    <TimeSpan>0:5:51.619_0:6:20.106</TimeSpan>
  </Marker>
  <Marker pid="109:2.9" seqId="18">
    <Start>0:6:20.106</Start>
    <End>0:6:48.189</End>
    <TimeSpan>0:6:20.106_0:6:48.189</TimeSpan>
  </Marker>
  <Marker pid="109:2.10" seqId="19">
    <Start>0:6:48.189</Start>
    <End>0:7:18.505</End>
    <TimeSpan>0:6:48.189_0:7:18.505</TimeSpan>
  </Marker>
  <Marker pid="109:2.11" seqId="20">
    <Start>0:7:18.505</Start>
    <End>0:7:31.694</End>
    <TimeSpan>0:7:18.505_0:7:31.694</TimeSpan>
  </Marker>
  <Marker pid="109:3.0" seqId="21">
    <Start>0:7:31.694</Start>
    <End>0:7:37.913</End>
    <TimeSpan>0:7:31.694_0:7:37.913</TimeSpan>
  </Marker>
  <Marker pid="109:3.1" seqId="22">
    <Start>0:7:37.913</Start>
    <End>0:8:18.563</End>
    <TimeSpan>0:7:37.913_0:8:18.563</TimeSpan>
  </Marker>
  <Marker pid="109:3.2" seqId="23">
    <Start>0:8:18.563</Start>
    <End>0:9:16.844</End>
    <TimeSpan>0:8:18.563_0:9:16.844</TimeSpan>
  </Marker>
  <Marker pid="109:3.3" seqId="24">
    <Start>0:9:16.844</Start>
    <End>0:9:59.776</End>
    <TimeSpan>0:9:16.844_0:9:59.776</TimeSpan>
  </Marker>
  <Marker pid="109:3.4" seqId="25">
    <Start>0:9:59.776</Start>
    <End>0:10:17.107</End>
    <TimeSpan>0:9:59.776_0:10:17.107</TimeSpan>
  </Marker>
  <Marker pid="109:3.5" seqId="26">
    <Start>0:10:17.107</Start>
    <End>0:10:37.695</End>
    <TimeSpan>0:10:17.107_0:10:37.695</TimeSpan>
  </Marker>
  <Marker pid="109:3.6" seqId="27">
    <Start>0:10:37.695</Start>
    <End>0:11:1.581</End>
    <TimeSpan>0:10:37.695_0:11:1.581</TimeSpan>
  </Marker>
  <Marker pid="109:3.7" seqId="28">
    <Start>0:11:1.581</Start>
    <End>0:11:35.76</End>
    <TimeSpan>0:11:1.581_0:11:35.76</TimeSpan>
  </Marker>
  <Marker pid="109:3.8" seqId="29">
    <Start>0:11:35.76</Start>
    <End>0:11:58.241</End>
    <TimeSpan>0:11:35.76_0:11:58.241</TimeSpan>
  </Marker>
  <Marker pid="109:4.0" seqId="30">
    <Start>0:11:58.241</Start>
    <End>0:12:4.13</End>
    <TimeSpan>0:11:58.241_0:12:4.13</TimeSpan>
  </Marker>
  <Marker pid="109:4.1" seqId="31">
    <Start>0:12:4.13</Start>
    <End>0:12:40.700</End>
    <TimeSpan>0:12:4.13_0:12:40.700</TimeSpan>
  </Marker>
  <Marker pid="109:4.2" seqId="32">
    <Start>0:12:40.700</Start>
    <End>0:13:7.542</End>
    <TimeSpan>0:12:40.700_0:13:7.542</TimeSpan>
  </Marker>
  <Marker pid="109:4.3" seqId="33">
    <Start>0:13:7.542</Start>
    <End>0:13:27.615</End>
    <TimeSpan>0:13:7.542_0:13:27.615</TimeSpan>
  </Marker>
  <Marker pid="109:4.4" seqId="34">
    <Start>0:13:27.615</Start>
    <End>0:13:57.729</End>
    <TimeSpan>0:13:27.615_0:13:57.729</TimeSpan>
  </Marker>
  <Marker pid="109:4.5" seqId="35">
    <Start>0:13:57.729</Start>
    <End>0:14:45.816</End>
    <TimeSpan>0:13:57.729_0:14:45.816</TimeSpan>
  </Marker>
  <Marker pid="109:4.6" seqId="36">
    <Start>0:14:45.816</Start>
    <End>0:15:12.954</End>
    <TimeSpan>0:14:45.816_0:15:12.954</TimeSpan>
  </Marker>
  <Marker pid="109:5.0" seqId="37">
    <Start>0:15:12.954</Start>
    <End>0:15:19.275</End>
    <TimeSpan>0:15:12.954_0:15:19.275</TimeSpan>
  </Marker>
  <Marker pid="109:5.1" seqId="38">
    <Start>0:15:19.275</Start>
    <End>0:16:4.179</End>
    <TimeSpan>0:15:19.275_0:16:4.179</TimeSpan>
  </Marker>
  <Marker pid="109:5.2" seqId="39">
    <Start>0:16:4.179</Start>
    <End>0:16:21.745</End>
    <TimeSpan>0:16:4.179_0:16:21.745</TimeSpan>
  </Marker>
  <Marker pid="109:5.3" seqId="40">
    <Start>0:16:21.745</Start>
    <End>0:17:12.639</End>
    <TimeSpan>0:16:21.745_0:17:12.639</TimeSpan>
  </Marker>
  <Marker pid="109:5.4" seqId="41">
    <Start>0:17:12.639</Start>
    <End>0:17:52.950</End>
    <TimeSpan>0:17:12.639_0:17:52.950</TimeSpan>
  </Marker>
  <Marker pid="109:5.5" seqId="42">
    <Start>0:17:52.950</Start>
    <End>0:18:39.346</End>
    <TimeSpan>0:17:52.950_0:18:39.346</TimeSpan>
  </Marker>
  <Marker pid="109:6.0" seqId="43">
    <Start>0:18:39.346</Start>
    <End>0:18:45.348</End>
    <TimeSpan>0:18:39.346_0:18:45.348</TimeSpan>
  </Marker>
  <Marker pid="109:6.1" seqId="44">
    <Start>0:18:45.348</Start>
    <End>0:19:36.598</End>
    <TimeSpan>0:18:45.348_0:19:36.598</TimeSpan>
  </Marker>
  <Marker pid="109:6.2" seqId="45">
    <Start>0:19:36.598</Start>
    <End>0:20:35.385</End>
    <TimeSpan>0:19:36.598_0:20:35.385</TimeSpan>
  </Marker>
  <Marker pid="109:6.3" seqId="46">
    <Start>0:20:35.385</Start>
    <End>0:21:16.149</End>
    <TimeSpan>0:20:35.385_0:21:16.149</TimeSpan>
  </Marker>
  <Marker pid="109:6.4" seqId="47">
    <Start>0:21:16.149</Start>
    <End>0:21:58.453</End>
    <TimeSpan>0:21:16.149_0:21:58.453</TimeSpan>
  </Marker>
  <Marker pid="109:6.5" seqId="48">
    <Start>0:21:58.453</Start>
    <End>0:22:24.11</End>
    <TimeSpan>0:21:58.453_0:22:24.11</TimeSpan>
  </Marker>
  <Marker pid="109:6.6" seqId="49">
    <Start>0:22:24.11</Start>
    <End>0:22:52.144</End>
    <TimeSpan>0:22:24.11_0:22:52.144</TimeSpan>
  </Marker>
  <Marker pid="109:6.7" seqId="50">
    <Start>0:22:52.144</Start>
    <End>0:23:17.156</End>
    <TimeSpan>0:22:52.144_0:23:17.156</TimeSpan>
  </Marker>
  <Marker pid="109:7.0" seqId="51">
    <Start>0:23:17.156</Start>
    <End>0:23:23.114</End>
    <TimeSpan>0:23:17.156_0:23:23.114</TimeSpan>
  </Marker>
  <Marker pid="109:7.1" seqId="52">
    <Start>0:23:23.114</Start>
    <End>0:23:55.618</End>
    <TimeSpan>0:23:23.114_0:23:55.618</TimeSpan>
  </Marker>
  <Marker pid="109:7.2" seqId="53">
    <Start>0:23:55.618</Start>
    <End>0:24:19.400</End>
    <TimeSpan>0:23:55.618_0:24:19.400</TimeSpan>
  </Marker>
  <Marker pid="109:7.3" seqId="54">
    <Start>0:24:19.400</Start>
    <End>0:24:48.920</End>
    <TimeSpan>0:24:19.400_0:24:48.920</TimeSpan>
  </Marker>
  <Marker pid="109:7.4" seqId="55">
    <Start>0:24:48.920</Start>
    <End>0:25:13.341</End>
    <TimeSpan>0:24:48.920_0:25:13.341</TimeSpan>
  </Marker>
  <Marker pid="109:7.5" seqId="56">
    <Start>0:25:13.341</Start>
    <End>0:25:46.583</End>
    <TimeSpan>0:25:13.341_0:25:46.583</TimeSpan>
  </Marker>
  <Marker pid="109:7.6" seqId="57">
    <Start>0:25:46.583</Start>
    <End>0:26:6.31</End>
    <TimeSpan>0:25:46.583_0:26:6.31</TimeSpan>
  </Marker>
  <Marker pid="109:7.7" seqId="58">
    <Start>0:26:6.31</Start>
    <End>0:27:2.811</End>
    <TimeSpan>0:26:6.31_0:27:2.811</TimeSpan>
  </Marker>
  <Marker pid="109:7.8" seqId="59">
    <Start>0:27:2.811</Start>
    <End>0:27:29.98</End>
    <TimeSpan>0:27:2.811_0:27:29.98</TimeSpan>
  </Marker>
  <Marker pid="109:7.9" seqId="60">
    <Start>0:27:29.98</Start>
    <End>0:27:33.630</End>
    <TimeSpan>0:27:29.98_0:27:33.630</TimeSpan>
  </Marker>
</AudioMarkers>